cq_filter/__init__.py
cq_filter/cq_filter.py
cq_filter/tests/__init__.py
cq_filter/tests/conftest.py
cq_filter/tests/test_filter.py
cq_filter/tests/test_last.py
cq_filter-0.0.3.dist-info/LICENSE
cq_filter-0.0.3.dist-info/METADATA
cq_filter-0.0.3.dist-info/WHEEL
cq_filter-0.0.3.dist-info/top_level.txt
cq_filter-0.0.3.dist-info/RECORD
