Metadata-Version: 2.1
Name: cq-filter
Version: 0.0.3
Summary: Cadquery object filtering framework
Author-email: Matti Eiden <snaipperi@gmail.com>
License: Apache License 2.0
Project-URL: Bug Tracker, https://github.com/voneiden/cq-filter/issues/
Project-URL: Documentation, https://github.com/voneiden/cq-filter/
Project-URL: Source Code, https://github.com/voneiden/cq-filter/
Keywords: cadquery,filter
Classifier: Programming Language :: Python :: 3
Classifier: Development Status :: 3 - Alpha
Classifier: License :: OSI Approved :: Apache Software License
Classifier: Operating System :: OS Independent
Requires-Python: >=3.10
License-File: LICENSE
